superduper_openai/__init__.py
superduper_openai/model.py
superduper_openai-0.10.0.dist-info/licenses/LICENSE
superduper_openai-0.10.0.dist-info/METADATA
superduper_openai-0.10.0.dist-info/WHEEL
superduper_openai-0.10.0.dist-info/top_level.txt
superduper_openai-0.10.0.dist-info/RECORD
