Metadata-Version: 2.4
Name: superduper_openai
Version: 0.10.0
Summary: Superduper allows users to work with openai API models.
Maintainer-email: "superduper.io, Inc." <opensource@superduper.io>
License: 
Project-URL: homepage, https://superduper.io
Project-URL: documentation, https://docs.superduper.io/docs/intro
Project-URL: source, https://github.com/superduper-io/superduper
Keywords: databases,mongodb,data-science,machine-learning,mlops,vector-database,ai
Requires-Python: >=3.10
License-File: LICENSE
Requires-Dist: numpy
Requires-Dist: openai>=1.1.2
Provides-Extra: test
Requires-Dist: vcrpy==5.1.0; extra == "test"
Requires-Dist: urllib3==2.2.3; extra == "test"
Dynamic: license-file
